energyscope/__init__.py
energyscope/colors.py
energyscope/datasets.py
energyscope/energyscope.py
energyscope/models.py
energyscope/plots.py
energyscope/result.py
energyscope/data/__init__.py
energyscope/data/datasets/core/td/ESTD_12TD.dat
energyscope/data/datasets/core/td/ESTD_data_core.dat
energyscope/data/datasets/infrastructure/quebec/2020/QC_data.dat
energyscope/data/datasets/infrastructure/quebec/2020/mob_params.dat
energyscope/data/datasets/infrastructure/quebec/2020/mob_techs_dist_B2D.dat
energyscope/data/datasets/infrastructure/quebec/2020/param_run_es_n.xlsx
energyscope/data/datasets/infrastructure/quebec/2020/quebec_demands.csv
energyscope/data/datasets/infrastructure/quebec/2020/quebec_resources.csv
energyscope/data/datasets/infrastructure/quebec/2020/quebec_technologies.csv
energyscope/data/datasets/infrastructure/quebec/2020/techs_B2D.dat
energyscope/data/datasets/infrastructure/quebec/td/quebec_td_demands.csv
energyscope/data/datasets/infrastructure/quebec/td/quebec_td_resources.csv
energyscope/data/datasets/infrastructure/quebec/td/quebec_td_technologies.csv
energyscope/data/datasets/infrastructure/quebec/transition/quebec_transition_demands.csv
energyscope/data/datasets/infrastructure/quebec/transition/quebec_transition_resources.csv
energyscope/data/datasets/infrastructure/quebec/transition/quebec_transition_technologies.csv
energyscope/data/datasets/infrastructure/switzerland/2050/data.dat
energyscope/data/datasets/infrastructure/switzerland/2050/param_run_es_n.xlsx
energyscope/data/datasets/infrastructure/switzerland/2050/techs.dat
energyscope/data/datasets/lca/ch/data.dat
energyscope/data/datasets/lca/ch/techs.dat
energyscope/data/datasets/lca/ch/techs_lcia.dat
energyscope/data/datasets/lca/ch/techs_lcia_JS.dat
energyscope/data/datasets/lca/ch/techs_mob.dat
energyscope/data/datasets/lca/ch/techs_pv.dat
energyscope/data/datasets/lca/quebec/2020/techs_lcia.dat
energyscope/data/models/core/td/ESTD_model_core.mod
energyscope-2.1.1.dist-info/METADATA
energyscope-2.1.1.dist-info/WHEEL
energyscope-2.1.1.dist-info/licenses/LICENSE
energyscope-2.1.1.dist-info/RECORD
