Metadata-Version: 2.4
Name: energyscope
Version: 2.1.1
Summary: Energy system modeling and analysis.
Project-URL: Homepage, https://library.energyscope.ch
Project-URL: Repository, https://gitlab.com/energyscope/energyscope
Project-URL: Issues, https://gitlab.com/energyscope/energyscope/-/issues
Author-email: Jonas Schnidrig <jonas.schnidrig@hevs.ch>, Arthur Chuat <arthur.chuat@epfl.ch>, Cyrille Platteau <cyrille.platteau@epfl.ch>
Maintainer-email: IPESE IT <it.ipese@epfl.ch>
License-File: LICENSE
Keywords: analysis,energy,energy system,modeling
Classifier: Development Status :: 4 - Beta
Classifier: Intended Audience :: Science/Research
Classifier: License :: OSI Approved :: Apache Software License
Classifier: Operating System :: OS Independent
Classifier: Programming Language :: Python :: 3
Requires-Python: >=3.9
Requires-Dist: amplpy<1.0.0,>=0.14.0
Requires-Dist: ipywidgets<9.0.0,>=8.1.7
Requires-Dist: nbformat<6.0.0,>=5.10.0
Requires-Dist: numpy<3.0.0,>=2.0.0
Requires-Dist: pandas<3.0.0,>=2.0.0
Requires-Dist: plotly<7.0.0,>=5.24.0
Requires-Dist: salib<2.0.0,>=1.5.0
Requires-Dist: seaborn<1.0.0,>=0.13.0
Provides-Extra: ampl-modules
Requires-Dist: ampl-module-base; extra == 'ampl-modules'
Requires-Dist: ampl-module-highs; extra == 'ampl-modules'
